conda_oci_mirror/__init__.py
conda_oci_mirror/_version.py
conda_oci_mirror/cli.py
conda_oci_mirror/decorators.py
conda_oci_mirror/defaults.py
conda_oci_mirror/helpers.py
conda_oci_mirror/logger.py
conda_oci_mirror/mirror.py
conda_oci_mirror/oras.py
conda_oci_mirror/package.py
conda_oci_mirror/repo.py
conda_oci_mirror/tasks.py
conda_oci_mirror/util.py
conda_oci_mirror/tests/conftest.py
conda_oci_mirror/tests/test_mirror.py
conda_oci_mirror/tests/test_package.py
conda_oci_mirror/tests/test_pushpull_cache.py
conda_oci_mirror/tests/test_repo.py
conda_oci_mirror/tests/test_repodata.json
conda_oci_mirror-0.2.3.dist-info/LICENSE
conda_oci_mirror-0.2.3.dist-info/METADATA
conda_oci_mirror-0.2.3.dist-info/WHEEL
conda_oci_mirror-0.2.3.dist-info/entry_points.txt
conda_oci_mirror-0.2.3.dist-info/top_level.txt
conda_oci_mirror-0.2.3.dist-info/RECORD
