Metadata-Version: 2.2
Name: conda-oci-mirror
Version: 0.2.3
Summary: Tools to mirror conda packages to an OCI registry.
Author-email: conda-oci-mirror team <conda_oci_mirror@issues.github.com>
License: BSD-3-Clause
Keywords: mamba,conda,oci
Classifier: Intended Audience :: Developers
Classifier: Intended Audience :: System Administrators
Classifier: Intended Audience :: Science/Research
Classifier: License :: OSI Approved :: BSD License
Classifier: Programming Language :: Python
Classifier: Programming Language :: Python :: 3.7
Classifier: Programming Language :: Python :: 3.8
Classifier: Programming Language :: Python :: 3.9
Classifier: Programming Language :: Python :: 3.10
Requires-Python: >=3.7
License-File: LICENSE
Requires-Dist: click
Requires-Dist: requests
Requires-Dist: oras==0.1.14
Requires-Dist: conda-package-handling
Requires-Dist: zstandard
Requires-Dist: packaging
